{
    "id": "UCW5aUJJMCFxGrfM-7FHPO3w",
    "header": {
        "name": "不求人",
        "image": "https://yt3.ggpht.com/ytc/AKedOLTmmPA5eoqbpiSyoqYMQMaRxZ34EYOZUSP8GWtH=s88-c-k-c0x00ffffff-no-rj",
        "bg": "https://yt3.ggpht.com/70OJMiEyrTqJdscd7VV7PX2xGH3mHL6l1_Dm1rQcO5EeKoXVBTUeGaOD2vl06rmUoGzpAxLc4Q=w1080-fcrop64=1,00005a57ffffa5a8-k-c0xffffffff-no-nd-rj"
    },
    "body": [
        {
            "type": "title_image",
            "data": {
                "title": "人設圖",
                "image_list": [
                    {
                        "image": "https://pbs.twimg.com/media/E-L-oFPUYAIyHgp?format=jpg&name=small",
                        "image_big": "https://pbs.twimg.com/media/E-L-oFPUYAIyHgp?format=jpg&name=medium"
                    }
                ]
            }
        },
        {
            "type": "title_content",
            "data": {
                "title": "描述",
                "content": "香港VTuber不求人\n\n以自給自足為目標，不求人。"
            }
        },
        {
            "type": "title_map",
            "data": {
                "title": "個人資料",
                "map_list": [
                    {
                        "key": "名字",
                        "content": "不求人",
                        "heightRate": "1"
                    },
                    {
                        "key": "生日",
                        "content": "12月30日",
                        "heightRate": "1"
                    },
                    {
                        "key": "身高",
                        "content": "160cm",
                        "heightRate": "1"
                    }
                ]
            }
        },
        {
            "type": "title_map",
            "data": {
                "title": "關於直播",
                "map_list": [
                    {
                        "key": "類別",
                        "content": "個人勢",
                        "heightRate": "1"
                    },
                    {
                        "key": "語言",
                        "content": "廣東話",
                        "heightRate": "1"
                    },
                    {
                        "key": "Fan Name Tag",
                        "content": "#木棍幫",
                        "heightRate": "1"
                    }
                ]
            }
        },
        {
            "type": "title_contact",
            "data": {
                "title": "更多聯絡方式",
                "content": [
                    {
                        "key": "youtube",
                        "path": "UCW5aUJJMCFxGrfM-7FHPO3w"
                    },
                    {
                        "key": "twitter",
                        "path": "backscratcher28"
                    }
                ]
            }
        },
        {
            "type": "title_youtube",
            "data": {
                "title": "推薦影片",
                "video_list": [
                    {
                        "video_code": "a2Fda4JiAUw",
                        "image": "https://i.ytimg.com/vi/a2Fda4JiAUw/mqdefault.jpg",
                        "title": "【香港VTuber】不求人 自己紹介 + 製作過程 (假)",
                        "author": "不求人"
                    },
                    {
                        "video_code": "MGWAYCSDJ0c",
                        "image": "https://i.ytimg.com/vi/MGWAYCSDJ0c/mqdefault.jpg",
                        "title": "【不求人開箱】咒術迴戰 虎杖悠仁 黏土人 + 碎碎諗",
                        "author": "不求人"
                    },
                    {
                        "video_code": "u546y4F0uIQ",
                        "image": "https://i.ytimg.com/vi/u546y4F0uIQ/mqdefault.jpg",
                        "title": "【ShowCase】Original Character 【Live2D】",
                        "author": "不求人"
                    },
                    {
                        "video_code": "hN8ftfkI2hY",
                        "image": "https://i.ytimg.com/vi/hN8ftfkI2hY/mqdefault.jpg",
                        "title": "【不求人開箱】咒術迴戰 伏黑惠 黏土人 + 超長吐嘈 【香港VTuber】",
                        "author": "不求人"
                    },
                    {
                        "video_code": "wPUR298ukso",
                        "image": "https://i.ytimg.com/vi/wPUR298ukso/mqdefault.jpg",
                        "title": "不求人的重大告知。",
                        "author": "不求人"
                    },
                    {
                        "video_code": "SxQ4E2bHt-I",
                        "image": "https://i.ytimg.com/vi/SxQ4E2bHt-I/mqdefault.jpg",
                        "title": "【不求人】畫畫台之拖稿人",
                        "author": "不求人"
                    },
                    {
                        "video_code": "yYbbasD9qzk",
                        "image": "https://i.ytimg.com/vi/yYbbasD9qzk/mqdefault.jpg",
                        "title": "【不求人極速開箱】咒術迴戰 五條悟 黏土人【香港VTuber】",
                        "author": "不求人"
                    },
                    {
                        "video_code": "CesZ1ywn9C8",
                        "image": "https://i.ytimg.com/vi/CesZ1ywn9C8/mqdefault.jpg",
                        "title": "小小告知。",
                        "author": "不求人"
                    },
                    {
                        "video_code": "ddTtu9daruA",
                        "image": "https://i.ytimg.com/vi/ddTtu9daruA/mqdefault.jpg",
                        "title": "【不求人自剪精華】人家，鹹濕，劇本王【符文工廠 5】",
                        "author": "不求人"
                    },
                    {
                        "video_code": "u_Rax4Bg81Q",
                        "image": "https://i.ytimg.com/vi/u_Rax4Bg81Q/mqdefault.jpg",
                        "title": "直播前刷好古代核心！",
                        "author": "不求人"
                    }
                ]
            }
        },
        {
            "type": "title_youtube",
            "data": {
                "title": "推薦重播",
                "video_list": [
                    {
                        "video_code": "6KytGQWX2JM",
                        "image": "https://i.ytimg.com/vi/6KytGQWX2JM/mqdefault.jpg",
                        "title": "我想玩薩爾達。",
                        "author": "不求人"
                    },
                    {
                        "video_code": "_PBSgjl5drQ",
                        "image": "https://i.ytimg.com/vi/_PBSgjl5drQ/mqdefault.jpg",
                        "title": "【畫畫台】來畫港V！【香港VTuber /  不求人】",
                        "author": "不求人"
                    },
                    {
                        "video_code": "ZNE93f_fXXo",
                        "image": "https://i.ytimg.com/vi/ZNE93f_fXXo/mqdefault.jpg",
                        "title": "一齊開六合彩。",
                        "author": "不求人"
                    },
                    {
                        "video_code": "m7BDoqD7IDo",
                        "image": "https://i.ytimg.com/vi/m7BDoqD7IDo/mqdefault.jpg",
                        "title": "【不求人】初次直播！【香港VTuber】",
                        "author": "不求人"
                    },
                    {
                        "video_code": "aIvaBg0aK3E",
                        "image": "https://i.ytimg.com/vi/aIvaBg0aK3E/mqdefault.jpg",
                        "title": "【畫畫台】超安靜地畫圖。【香港VTuber /  不求人】",
                        "author": "不求人"
                    },
                    {
                        "video_code": "A3usfFwPw9k",
                        "image": "https://i.ytimg.com/vi/A3usfFwPw9k/mqdefault.jpg",
                        "title": "【吹水台】第一次雜談。【香港VTuber /  不求人】",
                        "author": "不求人"
                    },
                    {
                        "video_code": "WO2IvkZBzzY",
                        "image": "https://i.ytimg.com/vi/WO2IvkZBzzY/mqdefault.jpg",
                        "title": "【畫畫台】畫有點點色的圖！【香港VTuber /  不求人】",
                        "author": "不求人"
                    },
                    {
                        "video_code": "ufVa22e_qo8",
                        "image": "https://i.ytimg.com/vi/ufVa22e_qo8/mqdefault.jpg",
                        "title": "【Minecraft】初次聯動！同涼子一齊整點陣圖！【香港VTuber /  不求人】",
                        "author": "不求人"
                    },
                    {
                        "video_code": "p7mk8FUS-0E",
                        "image": "https://i.ytimg.com/vi/p7mk8FUS-0E/mqdefault.jpg",
                        "title": "生存報告。",
                        "author": "不求人"
                    },
                    {
                        "video_code": "zQvGEnWqVHE",
                        "image": "https://i.ytimg.com/vi/zQvGEnWqVHE/mqdefault.jpg",
                        "title": "【影視台】睇炎柱沒有輸 with 姐棍。【香港VTuber /  不求人】",
                        "author": "不求人"
                    }
                ]
            }
        }
    ]
}